scrapypi/__init__.py
scrapypi/handler.py
scrapypi/scrapypi.py
scrapypi/stubs/__init__.pyi
scrapypi/stubs/scrapypi.pyi
scrapypi-0.0.8.dist-info/LICENCE.txt
scrapypi-0.0.8.dist-info/METADATA
scrapypi-0.0.8.dist-info/WHEEL
scrapypi-0.0.8.dist-info/entry_points.txt
scrapypi-0.0.8.dist-info/top_level.txt
scrapypi-0.0.8.dist-info/RECORD
