Metadata-Version: 2.1
Name: scrapypi
Version: 0.0.8
Summary: Get PyPi Package information.
Author: Erasmus A. Junior
Author-email: eirasmx@pm.me
License: GNU LGPLv3
Keywords: pypi,information,package,module,stats,info,scrape
Classifier: Development Status :: 3 - Alpha
Classifier: Environment :: Console
Classifier: License :: OSI Approved :: GNU Lesser General Public License v3 (LGPLv3)
Classifier: Operating System :: OS Independent
Classifier: Programming Language :: Python :: 3
Requires-Python: >=3.7
License-File: LICENCE.txt
Requires-Dist: requests
Requires-Dist: wget
